[{"id":1,"name":"Nescafé","category":{"id":"23","name":"cat1"},"quantity":1,"shortageQtyWarning":1,"active":true,"imgUrl":{"filename":"images/nescafe.jpg","filetype":"image/jpeg","value":""},"predictToBuy":0},{"id":2,"active":true,"name":"Ovos","category":{"id":"20","name":"Cat1"},"quantity":7,"shortageQtyWarning":3,"predictToBuy":1,"imgUrl":{"filename":"images/ovos.jpg","filetype":"image/jpeg","value":""}},{"id":3,"active":true,"name":"Shampoo H&S","category":{"id":"24","name":"Cat1"},"quantity":1,"shortageQtyWarning":0,"predictToBuy":1,"imgUrl":{"filename":"images/shampoohs.jpg","filetype":"image/jpeg","value":""}},{"id":4,"active":true,"name":"Kiwi","category":{"id":"5"},"quantity":7,"shortageQtyWarning":1,"predictToBuy":1,"imgUrl":{"filename":"images/kiwi.jpg","filetype":"image/jpeg","value":""}},{"id":5,"active":true,"name":"Detergente Loiça","category":{"id":"9"},"quantity":2,"shortageQtyWarning":1,"predictToBuy":1,"imgUrl":{"filename":"images/20180408005608.jpg","filetype":"image/jpeg","value":""}},{"id":6,"active":true,"name":"Bananas","category":{"id":"5"},"quantity":4,"shortageQtyWarning":2,"predictToBuy":1,"imgUrl":{"filename":"images/bananas.jpg","filetype":"image/jpeg","value":""}},{"id":7,"active":true,"name":"Salsichas","category":{"id":"22"},"quantity":3,"shortageQtyWarning":1,"predictToBuy":1,"imgUrl":{"filename":"images/salsichas.jpeg","filetype":"image/jpeg","value":""}},{"id":8,"active":true,"name":"Fraldas","category":{"id":"25"},"quantity":2,"shortageQtyWarning":1,"predictToBuy":1,"imgUrl":{"filename":"images/20180408003416.jpg","filetype":"image/jpeg","value":""}},{"id":9,"active":true,"name":"Batatas Fritas","category":{"id":"17"},"quantity":2,"shortageQtyWarning":1,"predictToBuy":1,"imgUrl":{"filename":"images/20180408003313.jpg","filetype":"image/jpeg","value":""}},{"id":10,"active":true,"name":"Papel de Cozinha","category":{"id":"21"},"quantity":4,"shortageQtyWarning":1,"predictToBuy":1,"imgUrl":{"filename":"images/20180408005918.jpg","filetype":"image/jpeg","value":""}},{"id":11,"active":true,"name":"Nesquik","category":{"id":"16"},"quantity":1,"shortageQtyWarning":0,"predictToBuy":1,"imgUrl":{"filename":"images/20180408005959.jpg","filetype":"image/jpeg","value":""}},{"id":12,"active":true,"name":"Batatas","category":{"id":"7"},"quantity":1,"shortageQtyWarning":0,"predictToBuy":1,"imgUrl":{"filename":"images/20180408003514.jpg","filetype":"image/jpeg","value":""}},{"id":13,"active":true,"name":"Iogurtes","category":{"id":"26"},"quantity":6,"shortageQtyWarning":0,"predictToBuy":1,"imgUrl":{"filename":"images/20180408004109.jpg","filetype":"image/jpeg","value":""}},{"id":14,"active":true,"name":"Cogumelos","category":{"id":"22"},"quantity":4,"shortageQtyWarning":1,"predictToBuy":1,"imgUrl":{"filename":"images/20180408003719.jpg","filetype":"image/jpeg","value":""}},{"id":15,"active":true,"name":"Bolachas Digestive","category":{"id":"2"},"quantity":3,"shortageQtyWarning":1,"predictToBuy":1,"imgUrl":{"filename":"images/20180408003944.jpg","filetype":"image/jpeg","value":""}},{"id":16,"active":true,"name":"Gelatina","category":{"id":"16"},"quantity":3,"shortageQtyWarning":1,"predictToBuy":1,"imgUrl":{"filename":"images/20180408004155.jpg","filetype":"image/jpeg","value":""}},{"id":17,"active":true,"name":"Vinho de Culinária","category":{"id":"17"},"quantity":2,"shortageQtyWarning":0,"predictToBuy":1,"imgUrl":{"filename":"images/20180408004452.jpg","filetype":"image/jpeg","value":""}},{"id":18,"active":true,"name":"Natas Culinária Normal","category":{"id":"26"},"quantity":2,"shortageQtyWarning":1,"predictToBuy":1,"imgUrl":{"filename":"images/20180408004502.jpg","filetype":"image/jpeg","value":""}},{"id":19,"active":true,"name":"Açucar","category":{"id":"12"},"quantity":1,"shortageQtyWarning":0,"predictToBuy":1,"imgUrl":{"filename":"images/15241387335672115131929.jpg","filetype":"image/jpeg","value":""}},{"id":20,"active":true,"name":"Natas Culinária 3 Pimentas","category":{"id":"26"},"quantity":0,"shortageQtyWarning":0,"predictToBuy":1,"imgUrl":{"filename":"images/20180408004601.jpg","filetype":"image/jpeg","value":""}},{"id":21,"active":true,"name":"Natas Culinária Caril","category":{"id":"26"},"quantity":1,"shortageQtyWarning":0,"predictToBuy":1,"imgUrl":{"filename":"images/20180408004611.jpg","filetype":"image/jpeg","value":""}},{"id":22,"active":true,"name":"Atum","category":{"id":"22"},"quantity":2,"shortageQtyWarning":1,"predictToBuy":1,"imgUrl":{"filename":"images/20180408004510.jpg","filetype":"image/jpeg","value":""}},{"id":23,"active":true,"name":"Polpa de Tomate","category":{"id":"17"},"quantity":3,"shortageQtyWarning":1,"predictToBuy":1,"imgUrl":{"filename":"images/1524139395741.jpg","filetype":"image/jpeg","value":""}},{"id":24,"active":true,"name":"Esparguete","category":{"id":"10"},"quantity":3,"shortageQtyWarning":1,"predictToBuy":1,"imgUrl":{"filename":"images/20180408004901.jpg","filetype":"image/jpeg","value":""}},{"id":25,"active":true,"name":"Arroz","category":{"id":"10"},"quantity":3,"shortageQtyWarning":1,"predictToBuy":1,"imgUrl":{"filename":"images/20180408004937.jpg","filetype":"image/jpeg","value":""}},{"id":26,"active":true,"name":"Chocolate culinária","category":{"id":"16"},"quantity":1,"shortageQtyWarning":0,"predictToBuy":1,"imgUrl":{"filename":"images/20180419130807.jpg","filetype":"image/jpeg","value":""}},{"id":27,"active":true,"name":"Mel","category":{"id":"12"},"quantity":1,"shortageQtyWarning":0,"predictToBuy":1,"imgUrl":{"filename":"images/20180419131232.jpg","filetype":"image/jpeg","value":""}},{"id":28,"active":true,"name":"Nutela","category":{"id":"16"},"quantity":1,"shortageQtyWarning":0,"predictToBuy":1,"imgUrl":{"filename":"images/20180408005053.jpg","filetype":"image/jpeg","value":""}},{"id":29,"active":true,"name":"Sal grosso","category":{"id":"4"},"quantity":1,"shortageQtyWarning":0,"predictToBuy":1,"imgUrl":{"filename":"images/20180419131640.jpg","filetype":"image/jpeg","value":""}},{"id":30,"active":true,"name":"Bolachas Maria","category":{"id":"2"},"quantity":1,"shortageQtyWarning":0,"predictToBuy":1,"imgUrl":{"filename":"images/20180419132253.jpg","filetype":"image/jpeg","value":""}},{"id":31,"active":true,"name":"Bolachas Palitos","category":{"id":"2"},"quantity":2,"shortageQtyWarning":0,"predictToBuy":1,"imgUrl":{"filename":"images/20180419132514.jpg","filetype":"image/jpeg","value":""}},{"id":32,"active":true,"name":"Caramelo","category":{"id":"17"},"quantity":1,"shortageQtyWarning":0,"predictToBuy":1,"imgUrl":{"filename":"images/20180419133335.jpg","filetype":"image/jpeg","value":""}},{"id":33,"active":true,"name":"Farinha para pizza","category":{"id":"11"},"quantity":1,"shortageQtyWarning":0,"predictToBuy":1,"imgUrl":{"filename":"images/20180419133217.jpg","filetype":"image/jpeg","value":""}},{"id":34,"active":true,"name":"Farinha para bolos","category":{"id":"11"},"quantity":1,"shortageQtyWarning":0,"predictToBuy":1,"imgUrl":{"filename":"images/20180419133237.jpg","filetype":"image/jpeg","value":""}},{"id":35,"active":true,"name":"Leite bebé","category":{"id":"26"},"quantity":2,"shortageQtyWarning":1,"predictToBuy":1,"imgUrl":{"filename":"images/20180419190844.jpg","filetype":"image/jpeg","value":""}},{"id":36,"active":true,"name":"Tostas","category":{"id":"2"},"quantity":1,"shortageQtyWarning":0,"predictToBuy":1,"imgUrl":{"filename":"images/20180419190815.jpg","filetype":"image/jpeg","value":""}},{"id":37,"active":true,"name":"Tomate Pelado int/trit","category":{"id":"22"},"quantity":3,"shortageQtyWarning":1,"predictToBuy":1,"imgUrl":{"filename":"images/20180419191229.jpg","filetype":"image/jpeg","value":""}},{"id":38,"active":true,"name":"Cebolas","category":{"id":"7"},"quantity":4,"shortageQtyWarning":2,"predictToBuy":1,"imgUrl":{"filename":"images/20180419191652.jpg","filetype":"image/jpeg","value":""}},{"id":39,"active":true,"name":"Sacos do Lixo","category":{"id":"9"},"quantity":2,"shortageQtyWarning":1,"predictToBuy":1,"imgUrl":{"filename":"images/sacoslixo.jpg","filetype":"image/jpeg","value":""}},{"id":40,"active":true,"name":"Guardanapos","category":{"id":"21"},"quantity":2,"shortageQtyWarning":1,"predictToBuy":1,"imgUrl":{"filename":"images/20180419195658.jpg","filetype":"image/jpeg","value":""}},{"id":41,"active":true,"name":"Pipocas salgadas","category":{"id":"16"},"quantity":1,"shortageQtyWarning":0,"predictToBuy":1,"imgUrl":{"filename":"images/20180408010010.jpg","filetype":"image/jpeg","value":""}},{"id":42,"active":true,"name":"Dodots","category":{"id":"25"},"quantity":2,"shortageQtyWarning":1,"predictToBuy":1,"imgUrl":{"filename":"images/20180408005736.jpg","filetype":"image/jpeg","value":""}},{"id":43,"active":true,"name":"Manteiga","category":{"id":"26"},"quantity":1,"shortageQtyWarning":1,"predictToBuy":1,"imgUrl":{"filename":"images/20180408004159.jpg","filetype":"image/jpeg","value":""}},{"id":44,"active":true,"name":"Maçãs","category":{"id":"5"},"quantity":2,"shortageQtyWarning":2,"predictToBuy":1,"imgUrl":""},{"id":45,"active":true,"name":"Pêras","category":{"id":"5"},"quantity":9,"shortageQtyWarning":2,"predictToBuy":1,"imgUrl":""},{"id":46,"active":true,"name":"Tangerinas","category":{"id":"5"},"quantity":3,"shortageQtyWarning":2,"predictToBuy":1,"imgUrl":""},{"id":47,"active":true,"name":"Uvas","category":{"id":"5"},"quantity":1,"shortageQtyWarning":0,"predictToBuy":1,"imgUrl":""},{"id":48,"active":true,"name":"Alface","category":{"id":"7"},"quantity":1,"shortageQtyWarning":0,"predictToBuy":1,"imgUrl":""},{"id":49,"active":true,"name":"Cenouras","category":{"id":"7"},"quantity":6,"shortageQtyWarning":2,"predictToBuy":1,"imgUrl":""},{"id":50,"active":true,"name":"Limões","category":{"id":"5"},"quantity":3,"shortageQtyWarning":1,"predictToBuy":1,"imgUrl":""},{"id":51,"active":true,"name":"Ketchup","category":{"id":"17"},"quantity":1,"shortageQtyWarning":0,"predictToBuy":1,"imgUrl":""},{"id":52,"active":true,"name":"Cerveja","category":{"id":1},"quantity":3,"shortageQtyWarning":0,"predictToBuy":1,"imgUrl":""},{"id":53,"active":true,"name":"Coentros","category":{"id":"4"},"quantity":1,"shortageQtyWarning":0,"predictToBuy":1,"imgUrl":""},{"id":54,"active":true,"name":"Salsa","category":{"id":"4"},"quantity":1,"shortageQtyWarning":0,"predictToBuy":1,"imgUrl":""},{"id":55,"active":true,"name":"Açafrão","category":{"id":"4"},"quantity":1,"shortageQtyWarning":0,"predictToBuy":1,"imgUrl":{"filename":"images/20180420155140.jpg","filetype":"image/jpeg","value":""}},{"id":56,"active":true,"name":"Pimentão Doce","category":{"id":"4"},"quantity":1,"shortageQtyWarning":0,"predictToBuy":1,"imgUrl":{"filename":"images/20180420155507.jpg","filetype":"image/jpeg","value":""}},{"id":57,"active":true,"name":"Sal de mesa","category":{"id":"4"},"quantity":1,"shortageQtyWarning":0,"predictToBuy":1,"imgUrl":{"filename":"images/20180420155450.jpg","filetype":"image/jpeg","value":""}},{"id":58,"active":true,"name":"Vinagre","category":{"id":"19"},"quantity":1,"shortageQtyWarning":0,"predictToBuy":1,"imgUrl":{"filename":"images/20180420155438.jpg","filetype":"image/jpeg","value":""}},{"id":59,"active":true,"name":"Azeite","category":{"id":"19"},"quantity":1,"shortageQtyWarning":0,"predictToBuy":1,"imgUrl":{"filename":"images/20180420155419.jpg","filetype":"image/jpeg","value":""}},{"id":60,"active":true,"name":"Pimenta Preta","category":{"id":"4"},"quantity":1,"shortageQtyWarning":0,"predictToBuy":1,"imgUrl":{"filename":"images/20180420155026.jpg","filetype":"image/jpeg","value":""}},{"id":61,"active":true,"name":"Oleo","category":{"id":"19"},"quantity":2,"shortageQtyWarning":1,"predictToBuy":1,"imgUrl":{"filename":"images/20180420155359.jpg","filetype":"image/jpeg","value":""}},{"id":62,"active":true,"name":"Piri-piri","category":{"id":"4"},"quantity":1,"shortageQtyWarning":0,"predictToBuy":1,"imgUrl":{"filename":"images/20180420155157.jpg","filetype":"image/jpeg","value":""}},{"id":63,"active":true,"name":"Sopa de cebola","category":{"id":"4"},"quantity":1,"shortageQtyWarning":0,"predictToBuy":1,"imgUrl":{"filename":"images/20180420155338.jpg","filetype":"image/jpeg","value":""}},{"id":64,"active":true,"name":"Alecrim","category":{"id":"4"},"quantity":1,"shortageQtyWarning":0,"predictToBuy":1,"imgUrl":{"filename":"images/20180420155321.jpg","filetype":"image/jpeg","value":""}},{"id":65,"active":true,"name":"Louro","category":{"id":"4"},"quantity":1,"shortageQtyWarning":0,"predictToBuy":1,"imgUrl":{"filename":"images/20180420155301.jpg","filetype":"image/jpeg","value":""}},{"id":66,"active":true,"name":"Pimenta Branca","category":{"id":"4"},"quantity":1,"shortageQtyWarning":0,"predictToBuy":1,"imgUrl":{"filename":"images/20180420155123.jpg","filetype":"image/jpeg","value":""}},{"id":67,"active":true,"name":"Canela","category":{"id":"4"},"quantity":1,"shortageQtyWarning":0,"predictToBuy":1,"imgUrl":{"filename":"images/20180420155107.jpg","filetype":"image/jpeg","value":""}},{"id":68,"active":true,"name":"Mangericão","category":{"id":"4"},"quantity":1,"shortageQtyWarning":0,"predictToBuy":1,"imgUrl":{"filename":"images/20180420155054.jpg","filetype":"image/jpeg","value":""}},{"id":69,"active":true,"name":"Orégãos","category":{"id":"4"},"quantity":1,"shortageQtyWarning":0,"predictToBuy":1,"imgUrl":{"filename":"images/20180420155040.jpg","filetype":"image/jpeg","value":""}},{"id":70,"active":true,"name":"Orégãos","category":{"id":"4"},"quantity":1,"shortageQtyWarning":0,"predictToBuy":1,"imgUrl":{"filename":"images/20180420155040.jpg","filetype":"image/jpeg","value":""}},{"id":71,"active":true,"name":"3 Pimentas","category":{"id":"4"},"quantity":1,"shortageQtyWarning":0,"predictToBuy":1,"imgUrl":{"filename":"images/20180420155011.jpg","filetype":"image/jpeg","value":""}},{"id":72,"active":true,"name":"Alhos","category":{"id":"7"},"quantity":4,"shortageQtyWarning":0,"predictToBuy":1,"imgUrl":{"filename":"images/20180420191642.jpg","filetype":"image/jpeg","value":""}},{"id":73,"active":true,"name":"Alho Francês","category":{"id":"7"},"quantity":1,"shortageQtyWarning":0,"predictToBuy":1,"imgUrl":{"filename":"images/20180420205249.jpg","filetype":"image/jpeg","value":""}},{"id":74,"active":true,"name":"Laranjas","category":{"id":"5"},"quantity":6,"shortageQtyWarning":0,"predictToBuy":1,"imgUrl":{"filename":"images/20180420191239.jpg","filetype":"image/jpeg","value":""}},{"id":75,"active":true,"name":"Natas para bater","category":{"id":"26"},"quantity":1,"shortageQtyWarning":0,"predictToBuy":1,"imgUrl":{"filename":"images/20180420205749.jpg","filetype":"image/jpeg","value":""}},{"id":76,"active":true,"name":"Rebentos de Soja","category":{"id":"22"},"quantity":1,"shortageQtyWarning":0,"predictToBuy":1,"imgUrl":{"filename":"images/20180420205929.jpg","filetype":"image/jpeg","value":""}},{"id":77,"active":true,"name":"Tomate Cherry","category":{"id":"7"},"quantity":1,"shortageQtyWarning":0,"predictToBuy":1,"imgUrl":{"filename":"images/20180420210224.jpg","filetype":"image/jpeg","value":""}},{"id":78,"active":true,"name":"Morangos","category":{"id":"5"},"quantity":1,"shortageQtyWarning":0,"predictToBuy":1,"imgUrl":{"filename":"images/20180420191134.jpg","filetype":"image/jpeg","value":""}},{"id":79,"active":true,"name":"Leite","category":{"id":"26"},"quantity":4,"shortageQtyWarning":2,"predictToBuy":1,"imgUrl":{"filename":"images/20180408003909.jpg","filetype":"image/jpeg","value":""}},{"id":80,"active":true,"name":"Sal de Máquina de Loiça","category":{"id":"9"},"quantity":0,"shortageQtyWarning":0,"predictToBuy":1,"imgUrl":""}]